[
  {
    "English": null,
    "ids": [
      "base_skill_effect_duration"
    ],
    "trade_stats": null,
    "hidden": null,
    "French": null,
    "German": null,
    "Japanese": null,
    "Korean": null,
    "Portuguese": null,
    "Russian": null,
    "Spanish": [
      {
        "condition": [
          {
            "min": 1000,
            "max": 1000,
            "negated": null
          }
        ],
        "format": [
          "#"
        ],
        "index_handlers": [
          [
            "milliseconds_to_seconds_2dp_if_required"
          ]
        ],
        "string": "Las brasas flotan durante {0} segundo",
        "reminder_text": null,
        "is_markup": null
      },
      {
        "condition": [
          {
            "min": null,
            "max": null,
            "negated": null
          }
        ],
        "format": [
          "#"
        ],
        "index_handlers": [
          [
            "milliseconds_to_seconds_2dp_if_required"
          ]
        ],
        "string": "Las brasas flotan durante {0} segundos",
        "reminder_text": null,
        "is_markup": null
      }
    ],
    "Thai": null,
    "Traditional_Chinese": null
  },
  {
    "English": null,
    "ids": [
      "blazing_cluster_maximum_number_of_projectiles_allowed"
    ],
    "trade_stats": null,
    "hidden": null,
    "French": null,
    "German": null,
    "Japanese": null,
    "Korean": null,
    "Portuguese": null,
    "Russian": null,
    "Spanish": [
      {
        "condition": [
          {
            "min": 2,
            "max": null,
            "negated": null
          }
        ],
        "format": [
          "#"
        ],
        "index_handlers": [
          []
        ],
        "string": "Máximo de brasas que se pueden acumular @{0}",
        "reminder_text": null,
        "is_markup": null
      },
      {
        "condition": [
          {
            "min": 2,
            "max": null,
            "negated": null
          }
        ],
        "format": [
          "#"
        ],
        "index_handlers": [
          []
        ],
        "string": "Puede acumular hasta {0} brasas\nLos modificadores de cantidad de [Projectile|proyectiles] se aplican\nen su lugar a la cantidad de brasas acumuladas",
        "reminder_text": null,
        "is_markup": null
      }
    ],
    "Thai": null,
    "Traditional_Chinese": null
  }
]