{
  "Dyad Crossbow":{
    "socketLimit":3,
    "tags":{
      "default":true
    },
    "implicit":"Loads an additional bolt",
    "req":{
      "level":20,
      "str":27
    },
    "weapon":{
      "PhysicalMin":9,
      "PhysicalMax":37,
      "CritChanceBase":5,
      "AttackRateBase":1.6,
      "Range":120,
      "ReloadTimeBase":1.1
    },
    "type":"Crossbow",
    "implicitModTypes":[["attack"]]
  },
  "Alloy Crossbow":{
    "tags":[],
    "req":{
      "level":26,
      "str":34
    },
    "weapon":{
      "PhysicalMin":12,
      "PhysicalMax":50,
      "AttackRateBase":1.7,
      "ReloadTimeBase":0.7
    },
    "implicitModTypes":[]
  },
  "Bombard Crossbow":{
    "tags":[],
    "implicit":"Grenade Skills Fire an additional Projectile",
    "req":{
      "level":33,
      "str":43
    },
    "weapon":{
      "PhysicalMin":14,
      "PhysicalMax":56,
      "AttackRateBase":1.65,
      "ReloadTimeBase":0.75
    },
    "implicitModTypes":[[]]
  },
  "Makeshift Crossbow":{
    "tags":[],
    "req":[],
    "weapon":{
      "PhysicalMin":7,
      "ReloadTimeBase":0.8
    },
    "implicitModTypes":[]
  },
  "Construct Crossbow":{
    "tags":[],
    "req":{
      "level":38,
      "str":49
    },
    "weapon":{
      "PhysicalMin":18,
      "PhysicalMax":72
    },
    "implicitModTypes":[]
  },
  "Blackfire Crossbow":{
    "tags":[],
    "req":{
      "level":45,
      "str":57
    },
    "weapon":{
      "PhysicalMax":80,
      "ReloadTimeBase":0.85
    },
    "implicitModTypes":[]
  },
  "Piercing Crossbow":{
    "tags":[],
    "implicit":"(20-30)% chance to Pierce an Enemy",
    "req":{
      "level":48,
      "str":61
    },
    "weapon":{
      "PhysicalMax":82
    },
    "implicitModTypes":[[]]
  },
  "Cumbrous Crossbow":{
    "tags":[],
    "implicit":"+1 to maximum number of Summoned Ballista Totems",
    "req":{
      "level":52,
      "str":66
    },
    "weapon":{
      "PhysicalMin":19,
      "PhysicalMax":76,
      "ReloadTimeBase":0.9
    },
    "implicitModTypes":[[]]
  },
  "Dedalian Crossbow":{
    "tags":[],
    "req":{
      "str":71
    },
    "weapon":{
      "PhysicalMin":25,
      "PhysicalMax":99,
      "AttackRateBase":1.55
    },
    "implicitModTypes":[]
  },
  "Esoteric Crossbow":{
    "tags":[],
    "req":{
      "level":65,
      "str":81
    },
    "weapon":{
      "PhysicalMin":28,
      "PhysicalMax":113
    },
    "implicitModTypes":[]
  },
  "Taut Crossbow":{
    "tags":[],
    "implicit":"(20-30)% increased Bolt Speed",
    "req":[],
    "weapon":{
      "PhysicalMax":79
    },
    "implicitModTypes":[[]]
  },
  "Robust Crossbow":{
    "tags":[],
    "req":[],
    "weapon":{
      "PhysicalMin":22,
      "PhysicalMax":89
    },
    "implicitModTypes":[]
  },
  "Painted Crossbow":{
    "tags":[],
    "req":{
      "level":51
    },
    "weapon":{
      "PhysicalMin":23,
      "PhysicalMax":92
    },
    "implicitModTypes":[]
  },
  "Twin Crossbow":{
    "tags":[],
    "req":{
      "level":55,
      "str":69
    },
    "weapon":{
      "PhysicalMin":21,
      "PhysicalMax":83
    },
    "implicitModTypes":[[]]
  },
  "Cannonade Crossbow":{
    "tags":[],
    "req":{
      "level":59,
      "str":74
    },
    "weapon":{
      "PhysicalMax":90
    },
    "implicitModTypes":[[]]
  },
  "Bleak Crossbow":{
    "tags":[],
    "req":{
      "level":62,
      "str":78
    },
    "weapon":{
      "PhysicalMax":109
    },
    "implicitModTypes":[]
  },
  "Stout Crossbow":{
    "tags":[],
    "req":{
      "level":67,
      "str":95
    },
    "weapon":{
      "PhysicalMin":30,
      "PhysicalMax":119
    },
    "implicitModTypes":[]
  },
  "Engraved Crossbow":{
    "tags":[],
    "req":{
      "str":106
    },
    "weapon":{
      "PhysicalMin":31,
      "PhysicalMax":124
    },
    "implicitModTypes":[]
  },
  "Tense Crossbow":{
    "tags":[],
    "req":{
      "dex":8
    },
    "weapon":{
      "PhysicalMax":15
    },
    "implicitModTypes":[[]]
  },
  "Gemini Crossbow":{
    "tags":[],
    "req":{
      "str":116
    },
    "weapon":{
      "PhysicalMax":112
    },
    "implicitModTypes":[[]]
  },
  "Siege Crossbow":{
    "tags":[],
    "req":[],
    "weapon":{
      "PhysicalMin":29,
      "PhysicalMax":115
    },
    "implicitModTypes":[[]]
  },
  "Desolate Crossbow":{
    "tags":[],
    "req":{
      "level":77
    },
    "weapon":{
      "PhysicalMax":132
    },
    "implicitModTypes":[]
  },
  "Sturdy Crossbow":{
    "tags":[],
    "req":{
      "level":10
    },
    "weapon":{
      "PhysicalMin":11
    },
    "implicitModTypes":[]
  },
  "Varnished Crossbow":{
    "tags":[],
    "req":{
      "level":16
    },
    "weapon":{
      "PhysicalMax":36
    },
    "implicitModTypes":[]
  },
  "Flexed Crossbow":{
    "tags":[],
    "req":[],
    "weapon":{
      "PhysicalMin":32,
      "PhysicalMax":127
    },
    "implicitModTypes":[[]]
  }
}