{
  "data": {
    "Default%": [
      0,
      0,
      0
    ],
    "MasterFile": "Metadata/Terrain/Gallows/Act2/2_13/Level_1/master_hub.tsi"
  },
  "edge_count": 0,
  "edge_types": {},
  "edges": [],
  "master": {
    "ChestData": "chests.cht",
    "Critters": "critters.clt",
    "Decals": "decals.dct",
    "EdgeCombination": "combination.ecf",
    "FillTiles": "random_fill_tiles_hub.gft",
    "MaterialsList": "materials.mtd",
    "MergeInsideWalls": null,
    "OuterBufferSize": null,
    "OuterGroundType": "Metadata/Terrain/black_inside_wall.gt",
    "RoomOverlap": null,
    "RoomSet": "generate_hub.rs",
    "RoomUnitSize": null,
    "StoreyHeight": null,
    "TileMaterialOverrides": "Metadata\\Terrain\\Gallows\\Leagues\\Sanctum\\material_overrides.tmo",
    "TileSet": "tiles_hub.tst",
    "version": null
  },
  "node_count": 1,
  "nodes": [
    {
      "numbers": [],
      "room": "entrance",
      "strings": [
        "default",
        "entrance1"
      ],
      "transform": "I",
      "unknown": [
        100,
        0,
        0,
        0,
        0,
        0,
        0,
        0,
        0,
        "N",
        0
      ],
      "x": 11,
      "y": 10
    }
  ],
  "numbers": [
    0
  ],
  "room_set": [],
  "size": [
    5,
    3
  ],
  "strings": [
    "",
    "",
    ""
  ],
  "tile_set": [],
  "version": 25
}