[
  {
    "English": null,
    "ids": [
      "skill_grant_X_power_charges_against_normal_and_magic_monsters",
      "skill_grant_X_power_charges_against_rare_monsters",
      "skill_grant_X_power_charges_against_unique_monsters"
    ],
    "trade_stats": null,
    "hidden": null,
    "French": null,
    "German": null,
    "Japanese": null,
    "Korean": null,
    "Portuguese": null,
    "Russian": null,
    "Spanish": [
      {
        "condition": [
          {
            "min": 1,
            "max": 1,
            "negated": null
          },
          {
            "min": 1,
            "max": 1,
            "negated": null
          },
          {
            "min": 1,
            "max": 1,
            "negated": null
          }
        ],
        "format": [
          "ignore",
          "ignore",
          "#"
        ],
        "index_handlers": [
          [],
          [],
          []
        ],
        "string": "Usar golpe de gracia en un monstruo otorga {2} [Charges|carga de poder]",
        "reminder_text": null,
        "is_markup": null
      },
      {
        "condition": [
          {
            "min": 1,
            "max": 1,
            "negated": null
          },
          {
            "min": 1,
            "max": 1,
            "negated": null
          },
          {
            "min": null,
            "max": null,
            "negated": null
          }
        ],
        "format": [
          "#",
          "#",
          "#"
        ],
        "index_handlers": [
          [],
          [],
          []
        ],
        "string": "Los monstruos [Rarity|normales y mágicos] otorgan {0} [Charges|carga de poder]\nLos monstruos [Rarity|raros] otorgan {1} [Charges|carga de poder]\nLos monstruos [Rarity|únicos] otorgan {2} [Charges|cargas de poder]",
        "reminder_text": null,
        "is_markup": null
      },
      {
        "condition": [
          {
            "min": 1,
            "max": 1,
            "negated": null
          },
          {
            "min": null,
            "max": null,
            "negated": null
          },
          {
            "min": 1,
            "max": 1,
            "negated": null
          }
        ],
        "format": [
          "#",
          "#",
          "#"
        ],
        "index_handlers": [
          [],
          [],
          []
        ],
        "string": "Los monstruos [Rarity|normales y mágicos] otorgan {0} [Charges|carga de poder]\nLos monstruos [Rarity|raros] otorgan {1} [Charges|cargas de poder]\nLos monstruos [Rarity|únicos] otorgan {2} [Charges|carga de poder]",
        "reminder_text": null,
        "is_markup": null
      },
      {
        "condition": [
          {
            "min": null,
            "max": null,
            "negated": null
          },
          {
            "min": 1,
            "max": 1,
            "negated": null
          },
          {
            "min": 1,
            "max": 1,
            "negated": null
          }
        ],
        "format": [
          "#",
          "#",
          "#"
        ],
        "index_handlers": [
          [],
          [],
          []
        ],
        "string": "Los monstruos [Rarity|normales y mágicos] otorgan {0} [Charges|cargas de poder]\nLos monstruos [Rarity|raros] otorgan {1} [Charges|carga de poder]\nLos monstruos [Rarity|únicos] otorgan {2} [Charges|carga de poder]",
        "reminder_text": null,
        "is_markup": null
      },
      {
        "condition": [
          {
            "min": null,
            "max": null,
            "negated": null
          },
          {
            "min": 1,
            "max": 1,
            "negated": null
          },
          {
            "min": null,
            "max": null,
            "negated": null
          }
        ],
        "format": [
          "#",
          "#",
          "#"
        ],
        "index_handlers": [
          [],
          [],
          []
        ],
        "string": "Los monstruos [Rarity|normales y mágicos] otorgan {0} [Charges|cargas de poder]\nLos monstruos [Rarity|raros] otorgan {1} [Charges|carga de poder]\nLos monstruos [Rarity|únicos] otorgan {2} [Charges|cargas de poder]",
        "reminder_text": null,
        "is_markup": null
      },
      {
        "condition": [
          {
            "min": null,
            "max": null,
            "negated": null
          },
          {
            "min": null,
            "max": null,
            "negated": null
          },
          {
            "min": 1,
            "max": 1,
            "negated": null
          }
        ],
        "format": [
          "#",
          "#",
          "#"
        ],
        "index_handlers": [
          [],
          [],
          []
        ],
        "string": "Los monstruos [Rarity|normales y mágicos] otorgan {0} [Charges|cargas de poder]\nLos monstruos [Rarity|raros] otorgan {1} [Charges|cargas de poder]\nLos monstruos [Rarity|únicos] otorgan {2} [Charges|carga de poder]",
        "reminder_text": null,
        "is_markup": null
      },
      {
        "condition": [
          {
            "min": 1,
            "max": 1,
            "negated": null
          },
          {
            "min": null,
            "max": null,
            "negated": null
          },
          {
            "min": null,
            "max": null,
            "negated": null
          }
        ],
        "format": [
          "#",
          "#",
          "#"
        ],
        "index_handlers": [
          [],
          [],
          []
        ],
        "string": "Los monstruos [Rarity|normales y mágicos] otorgan {0} [Charges|carga de poder]\nLos monstruos [Rarity|raros] otorgan {1} [Charges|cargas de poder]\nLos monstruos [Rarity|únicos] otorgan {2} [Charges|cargas de poder]",
        "reminder_text": null,
        "is_markup": null
      },
      {
        "condition": [
          {
            "min": null,
            "max": null,
            "negated": null
          },
          {
            "min": null,
            "max": null,
            "negated": null
          },
          {
            "min": null,
            "max": null,
            "negated": null
          }
        ],
        "format": [
          "#",
          "#",
          "#"
        ],
        "index_handlers": [
          [],
          [],
          []
        ],
        "string": "Los monstruos [Rarity|normales y mágicos] otorgan {0} [Charges|cargas de poder]\nLos monstruos [Rarity|raros] otorgan {1} [Charges|cargas de poder]\nLos monstruos [Rarity|únicos] otorgan {2} [Charges|cargas de poder]",
        "reminder_text": null,
        "is_markup": null
      }
    ],
    "Thai": null,
    "Traditional_Chinese": null
  }
]