[
  {
    "English": null,
    "ids": [
      "active_skill_base_area_of_effect_radius"
    ],
    "trade_stats": null,
    "hidden": null,
    "French": null,
    "German": null,
    "Japanese": null,
    "Korean": null,
    "Portuguese": null,
    "Russian": null,
    "Spanish": null,
    "Thai": null,
    "Traditional_Chinese": [
      {
        "condition": [
          {
            "min": 10,
            "max": 10,
            "negated": null
          }
        ],
        "format": [
          "#"
        ],
        "index_handlers": [
          [
            "divide_by_ten_1dp_if_required"
          ]
        ],
        "string": "戰吼範圍為 {0} 公尺",
        "reminder_text": null,
        "is_markup": null
      },
      {
        "condition": [
          {
            "min": null,
            "max": null,
            "negated": null
          }
        ],
        "format": [
          "#"
        ],
        "index_handlers": [
          [
            "divide_by_ten_1dp_if_required"
          ]
        ],
        "string": "戰吼範圍為 {0} 公尺",
        "reminder_text": null,
        "is_markup": null
      }
    ]
  },
  {
    "English": null,
    "ids": [
      "seismic_cry_slam_skill_aftershock_damage_+%_final"
    ],
    "trade_stats": null,
    "hidden": null,
    "French": null,
    "German": null,
    "Japanese": null,
    "Korean": null,
    "Portuguese": null,
    "Russian": null,
    "Spanish": null,
    "Thai": null,
    "Traditional_Chinese": [
      {
        "condition": [
          {
            "min": 1,
            "max": null,
            "negated": null
          }
        ],
        "format": [
          "#"
        ],
        "index_handlers": [
          []
        ],
        "string": "更多[Empowered|強化][Attack|攻擊][Aftershock|餘震]傷害@{0}%",
        "reminder_text": null,
        "is_markup": null
      },
      {
        "condition": [
          {
            "min": 1,
            "max": null,
            "negated": null
          }
        ],
        "format": [
          "#"
        ],
        "index_handlers": [
          []
        ],
        "string": "[Empowered|強化][Attack|攻擊][Aftershock|餘震]造成 {0}% 更多傷害",
        "reminder_text": null,
        "is_markup": null
      },
      {
        "condition": [
          {
            "min": null,
            "max": -1,
            "negated": null
          }
        ],
        "format": [
          "#"
        ],
        "index_handlers": [
          [
            "negate"
          ]
        ],
        "string": "[Empowered|強化][Attack|攻擊][Aftershock|餘震]造成 {0}% 更少傷害",
        "reminder_text": null,
        "is_markup": null
      }
    ]
  },
  {
    "English": null,
    "ids": [
      "warcry_empowers_per_X_monster_power",
      "warcry_empowers_per_X_monster_power_mp_cap"
    ],
    "trade_stats": null,
    "hidden": null,
    "French": null,
    "German": null,
    "Japanese": null,
    "Korean": null,
    "Portuguese": null,
    "Russian": null,
    "Spanish": null,
    "Thai": null,
    "Traditional_Chinese": [
      {
        "condition": [
          {
            "min": null,
            "max": null,
            "negated": null
          },
          {
            "min": null,
            "max": null,
            "negated": null
          }
        ],
        "format": [
          "#",
          "#"
        ],
        "index_handlers": [
          [],
          []
        ],
        "string": "每次[Empowered|強化][Slam|重擊]所需敵人[Power|強度]（最高）@{0} ({1})",
        "reminder_text": null,
        "is_markup": null
      },
      {
        "condition": [
          {
            "min": 1,
            "max": 1,
            "negated": null
          },
          {
            "min": null,
            "max": null,
            "negated": null
          }
        ],
        "format": [
          "ignore",
          "#"
        ],
        "index_handlers": [
          [],
          []
        ],
        "string": "每個範圍內的敵人[Power|強度]會[Empowered|強化] 1 次\n[Slam|重擊]，計算上限為 {1} [Power|強度]",
        "reminder_text": null,
        "is_markup": null
      },
      {
        "condition": [
          {
            "min": null,
            "max": null,
            "negated": null
          },
          {
            "min": null,
            "max": null,
            "negated": null
          }
        ],
        "format": [
          "#",
          "#"
        ],
        "index_handlers": [
          [],
          []
        ],
        "string": "每 {0} 個範圍內的敵人[Power|強度]會[Empowered|強化] 1 次\n[Slam|重擊]，計算上限為 {1} [Power|強度]",
        "reminder_text": null,
        "is_markup": null
      }
    ]
  }
]