{
  "data": {
    "Default%": [
      0,
      0,
      0
    ],
    "MasterFile": "Metadata/Terrain/Maps/UniqueVault/master.tsi"
  },
  "edge_count": 63,
  "edge_types": {
    "rooms": "rooms #FF5A5A5A\nwildcard\nwildcard\n0 1 0 0 1\n",
    "void": "void #FF141414\nwildcard\nwildcard\n0 1 0\n"
  },
  "edges": [
    {
      "color": "#FF141414",
      "edge_type": "void",
      "from": 0,
      "path": [],
      "to": 1,
      "unknown": [
        100,
        0,
        0,
        "Metadata/Terrain/Tools/void.et",
        0,
        0,
        0,
        "",
        0,
        "",
        0,
        0,
        "P",
        "V",
        1
      ]
    },
    {
      "color": "#FF141414",
      "edge_type": "void",
      "from": 2,
      "path": [],
      "to": 3,
      "unknown": [
        100,
        0,
        0,
        "Metadata/Terrain/Tools/void.et",
        0,
        0,
        0,
        "",
        0,
        "",
        0,
        0,
        "P",
        "V",
        1
      ]
    },
    {
      "color": "#FF141414",
      "edge_type": "void",
      "from": 18,
      "path": [],
      "to": 4,
      "unknown": [
        100,
        0,
        0,
        "Metadata/Terrain/Tools/void.et",
        0,
        0,
        0,
        "",
        0,
        "",
        0,
        0,
        "P",
        "V",
        1
      ]
    },
    {
      "color": "#FF141414",
      "edge_type": "void",
      "from": 5,
      "path": [],
      "to": 6,
      "unknown": [
        100,
        0,
        0,
        "Metadata/Terrain/Tools/void.et",
        0,
        0,
        0,
        "",
        0,
        "",
        0,
        0,
        "P",
        "V",
        1
      ]
    },
    {
      "color": "#FF141414",
      "edge_type": "void",
      "from": 19,
      "path": [],
      "to": 7,
      "unknown": [
        100,
        0,
        0,
        "Metadata/Terrain/Tools/void.et",
        0,
        0,
        0,
        "",
        0,
        "",
        0,
        0,
        "P",
        "V",
        1
      ]
    },
    {
      "color": "#FF141414",
      "edge_type": "void",
      "from": 12,
      "path": [],
      "to": 13,
      "unknown": [
        100,
        0,
        0,
        "Metadata/Terrain/Tools/void.et",
        0,
        0,
        0,
        "",
        0,
        "",
        0,
        0,
        "P",
        "V",
        1
      ]
    },
    {
      "color": "#FF141414",
      "edge_type": "void",
      "from": 14,
      "path": [],
      "to": 15,
      "unknown": [
        100,
        0,
        0,
        "Metadata/Terrain/Tools/void.et",
        0,
        0,
        0,
        "",
        0,
        "",
        0,
        0,
        "P",
        "V",
        1
      ]
    },
    {
      "color": "#FF141414",
      "edge_type": "void",
      "from": 16,
      "path": [],
      "to": 17,
      "unknown": [
        100,
        0,
        0,
        "Metadata/Terrain/Tools/void.et",
        0,
        0,
        0,
        "",
        0,
        "",
        0,
        0,
        "P",
        "V",
        1
      ]
    },
    {
      "color": "#FF5A5A5A",
      "edge_type": "rooms",
      "from": 42,
      "path": [],
      "to": 9,
      "unknown": [
        100,
        0,
        0,
        "Metadata/Terrain/Dungeon/rooms.et",
        0,
        0,
        0,
        "",
        0,
        "",
        0,
        0,
        "P",
        "N",
        1
      ]
    },
    {
      "color": "#FF5A5A5A",
      "edge_type": "rooms",
      "from": 24,
      "path": [],
      "to": 21,
      "unknown": [
        100,
        0,
        0,
        "Metadata/Terrain/Dungeon/rooms.et",
        0,
        0,
        0,
        "",
        0,
        "",
        0,
        0,
        "P",
        "N",
        1
      ]
    },
    {
      "color": "#FF5A5A5A",
      "edge_type": "rooms",
      "from": 47,
      "path": [],
      "to": 23,
      "unknown": [
        100,
        0,
        0,
        "Metadata/Terrain/Dungeon/rooms.et",
        0,
        0,
        0,
        "",
        0,
        "",
        0,
        0,
        "P",
        "N",
        1
      ]
    },
    {
      "color": "#FF5A5A5A",
      "edge_type": "rooms",
      "from": 9,
      "path": [],
      "to": 24,
      "unknown": [
        100,
        0,
        0,
        "Metadata/Terrain/Dungeon/rooms.et",
        0,
        0,
        0,
        "",
        0,
        "",
        0,
        0,
        "P",
        "N",
        1
      ]
    },
    {
      "color": "#FF5A5A5A",
      "edge_type": "rooms",
      "from": 23,
      "path": [],
      "to": 9,
      "unknown": [
        100,
        0,
        0,
        "Metadata/Terrain/Dungeon/rooms.et",
        0,
        0,
        0,
        "",
        0,
        "",
        0,
        0,
        "P",
        "N",
        1
      ]
    },
    {
      "color": "#FF5A5A5A",
      "edge_type": "rooms",
      "from": 43,
      "path": [],
      "to": 28,
      "unknown": [
        100,
        0,
        0,
        "Metadata/Terrain/Dungeon/rooms.et",
        0,
        0,
        0,
        "",
        0,
        "",
        0,
        0,
        "P",
        "N",
        1
      ]
    },
    {
      "color": "#FF5A5A5A",
      "edge_type": "rooms",
      "from": 44,
      "path": [],
      "to": 30,
      "unknown": [
        100,
        0,
        0,
        "Metadata/Terrain/Dungeon/rooms.et",
        0,
        0,
        0,
        "",
        0,
        "",
        0,
        0,
        "P",
        "N",
        1
      ]
    },
    {
      "color": "#FF5A5A5A",
      "edge_type": "rooms",
      "from": 53,
      "path": [],
      "to": 32,
      "unknown": [
        100,
        0,
        0,
        "Metadata/Terrain/Dungeon/rooms.et",
        0,
        0,
        0,
        "",
        0,
        "",
        0,
        0,
        "P",
        "N",
        1
      ]
    },
    {
      "color": "#FF5A5A5A",
      "edge_type": "rooms",
      "from": 33,
      "path": [],
      "to": 34,
      "unknown": [
        100,
        0,
        0,
        "Metadata/Terrain/Dungeon/rooms.et",
        0,
        0,
        0,
        "",
        0,
        "",
        0,
        0,
        "P",
        "N",
        1
      ]
    },
    {
      "color": "#FF5A5A5A",
      "edge_type": "rooms",
      "from": 35,
      "path": [],
      "to": 36,
      "unknown": [
        100,
        0,
        0,
        "Metadata/Terrain/Dungeon/rooms.et",
        0,
        0,
        0,
        "",
        0,
        "",
        0,
        0,
        "P",
        "N",
        1
      ]
    },
    {
      "color": "#FF5A5A5A",
      "edge_type": "rooms",
      "from": 50,
      "path": [],
      "to": 38,
      "unknown": [
        100,
        0,
        0,
        "Metadata/Terrain/Dungeon/rooms.et",
        0,
        0,
        0,
        "",
        0,
        "",
        0,
        0,
        "P",
        "N",
        1
      ]
    },
    {
      "color": "#FF5A5A5A",
      "edge_type": "rooms",
      "from": 46,
      "path": [],
      "to": 40,
      "unknown": [
        100,
        0,
        0,
        "Metadata/Terrain/Dungeon/rooms.et",
        0,
        0,
        0,
        "",
        0,
        "",
        0,
        0,
        "P",
        "N",
        1
      ]
    },
    {
      "color": "#FF5A5A5A",
      "edge_type": "rooms",
      "from": 45,
      "path": [],
      "to": 26,
      "unknown": [
        100,
        0,
        0,
        "Metadata/Terrain/Dungeon/rooms.et",
        0,
        0,
        0,
        "",
        0,
        "",
        0,
        0,
        "P",
        "N",
        1
      ]
    },
    {
      "color": "#FF5A5A5A",
      "edge_type": "rooms",
      "from": 25,
      "path": [],
      "to": 20,
      "unknown": [
        100,
        0,
        0,
        "Metadata/Terrain/Dungeon/rooms.et",
        0,
        0,
        0,
        "",
        0,
        "",
        0,
        0,
        "P",
        "N",
        1
      ]
    },
    {
      "color": "#FF5A5A5A",
      "edge_type": "rooms",
      "from": 39,
      "path": [],
      "to": 20,
      "unknown": [
        100,
        0,
        0,
        "Metadata/Terrain/Dungeon/rooms.et",
        0,
        0,
        0,
        "",
        0,
        "",
        0,
        0,
        "P",
        "N",
        1
      ]
    },
    {
      "color": "#FF5A5A5A",
      "edge_type": "rooms",
      "from": 52,
      "path": [],
      "to": 27,
      "unknown": [
        100,
        0,
        0,
        "Metadata/Terrain/Dungeon/rooms.et",
        0,
        0,
        0,
        "",
        0,
        "",
        0,
        0,
        "P",
        "N",
        1
      ]
    },
    {
      "color": "#FF5A5A5A",
      "edge_type": "rooms",
      "from": 51,
      "path": [],
      "to": 29,
      "unknown": [
        100,
        0,
        0,
        "Metadata/Terrain/Dungeon/rooms.et",
        0,
        0,
        0,
        "",
        0,
        "",
        0,
        0,
        "P",
        "N",
        1
      ]
    },
    {
      "color": "#FF5A5A5A",
      "edge_type": "rooms",
      "from": 11,
      "path": [],
      "to": 31,
      "unknown": [
        100,
        0,
        0,
        "Metadata/Terrain/Dungeon/rooms.et",
        0,
        0,
        0,
        "",
        0,
        "",
        0,
        0,
        "P",
        "N",
        1
      ]
    },
    {
      "color": "#FF5A5A5A",
      "edge_type": "rooms",
      "from": 11,
      "path": [],
      "to": 33,
      "unknown": [
        100,
        0,
        0,
        "Metadata/Terrain/Dungeon/rooms.et",
        0,
        0,
        0,
        "",
        0,
        "",
        0,
        0,
        "P",
        "N",
        1
      ]
    },
    {
      "color": "#FF5A5A5A",
      "edge_type": "rooms",
      "from": 11,
      "path": [],
      "to": 37,
      "unknown": [
        100,
        0,
        0,
        "Metadata/Terrain/Dungeon/rooms.et",
        0,
        0,
        0,
        "",
        0,
        "",
        0,
        0,
        "P",
        "N",
        1
      ]
    },
    {
      "color": "#FF5A5A5A",
      "edge_type": "rooms",
      "from": 11,
      "path": [],
      "to": 35,
      "unknown": [
        100,
        0,
        0,
        "Metadata/Terrain/Dungeon/rooms.et",
        0,
        0,
        0,
        "",
        0,
        "",
        0,
        0,
        "P",
        "N",
        1
      ]
    },
    {
      "color": "#FF5A5A5A",
      "edge_type": "rooms",
      "from": 41,
      "path": [],
      "to": 9,
      "unknown": [
        100,
        0,
        0,
        "Metadata/Terrain/Dungeon/rooms.et",
        0,
        0,
        0,
        "",
        0,
        "",
        0,
        0,
        "P",
        "N",
        1
      ]
    },
    {
      "color": "#FF5A5A5A",
      "edge_type": "rooms",
      "from": 27,
      "path": [],
      "to": 43,
      "unknown": [
        100,
        0,
        0,
        "Metadata/Terrain/Dungeon/rooms.et",
        0,
        0,
        0,
        "",
        0,
        "",
        0,
        0,
        "P",
        "N",
        1
      ]
    },
    {
      "color": "#FF5A5A5A",
      "edge_type": "rooms",
      "from": 29,
      "path": [],
      "to": 44,
      "unknown": [
        100,
        0,
        0,
        "Metadata/Terrain/Dungeon/rooms.et",
        0,
        0,
        0,
        "",
        0,
        "",
        0,
        0,
        "P",
        "N",
        1
      ]
    },
    {
      "color": "#FF5A5A5A",
      "edge_type": "rooms",
      "from": 43,
      "path": [],
      "to": 44,
      "unknown": [
        100,
        0,
        0,
        "Metadata/Terrain/Dungeon/rooms.et",
        0,
        0,
        0,
        "",
        0,
        "",
        0,
        0,
        "P",
        "N",
        1
      ]
    },
    {
      "color": "#FF5A5A5A",
      "edge_type": "rooms",
      "from": 48,
      "path": [],
      "to": 45,
      "unknown": [
        100,
        0,
        0,
        "Metadata/Terrain/Dungeon/rooms.et",
        0,
        0,
        0,
        "",
        0,
        "",
        0,
        0,
        "P",
        "N",
        1
      ]
    },
    {
      "color": "#FF5A5A5A",
      "edge_type": "rooms",
      "from": 49,
      "path": [],
      "to": 46,
      "unknown": [
        100,
        0,
        0,
        "Metadata/Terrain/Dungeon/rooms.et",
        0,
        0,
        0,
        "",
        0,
        "",
        0,
        0,
        "P",
        "N",
        1
      ]
    },
    {
      "color": "#FF5A5A5A",
      "edge_type": "rooms",
      "from": 45,
      "path": [],
      "to": 46,
      "unknown": [
        100,
        0,
        0,
        "Metadata/Terrain/Dungeon/rooms.et",
        0,
        0,
        0,
        "",
        0,
        "",
        0,
        0,
        "P",
        "N",
        1
      ]
    },
    {
      "color": "#FF5A5A5A",
      "edge_type": "rooms",
      "from": 22,
      "path": [],
      "to": 47,
      "unknown": [
        100,
        0,
        0,
        "Metadata/Terrain/Dungeon/rooms.et",
        0,
        0,
        0,
        "",
        0,
        "",
        0,
        0,
        "P",
        "N",
        1
      ]
    },
    {
      "color": "#FF5A5A5A",
      "edge_type": "rooms",
      "from": 25,
      "path": [],
      "to": 48,
      "unknown": [
        100,
        0,
        0,
        "Metadata/Terrain/Dungeon/rooms.et",
        0,
        0,
        0,
        "",
        0,
        "",
        0,
        0,
        "P",
        "N",
        1
      ]
    },
    {
      "color": "#FF5A5A5A",
      "edge_type": "rooms",
      "from": 39,
      "path": [],
      "to": 49,
      "unknown": [
        100,
        0,
        0,
        "Metadata/Terrain/Dungeon/rooms.et",
        0,
        0,
        0,
        "",
        0,
        "",
        0,
        0,
        "P",
        "N",
        1
      ]
    },
    {
      "color": "#FF5A5A5A",
      "edge_type": "rooms",
      "from": 37,
      "path": [],
      "to": 50,
      "unknown": [
        100,
        0,
        0,
        "Metadata/Terrain/Dungeon/rooms.et",
        0,
        0,
        0,
        "",
        0,
        "",
        0,
        0,
        "P",
        "N",
        1
      ]
    },
    {
      "color": "#FF5A5A5A",
      "edge_type": "rooms",
      "from": 20,
      "path": [],
      "to": 51,
      "unknown": [
        100,
        0,
        0,
        "Metadata/Terrain/Dungeon/rooms.et",
        0,
        0,
        0,
        "",
        0,
        "",
        0,
        0,
        "P",
        "N",
        1
      ]
    },
    {
      "color": "#FF5A5A5A",
      "edge_type": "rooms",
      "from": 20,
      "path": [],
      "to": 52,
      "unknown": [
        100,
        0,
        0,
        "Metadata/Terrain/Dungeon/rooms.et",
        0,
        0,
        0,
        "",
        0,
        "",
        0,
        0,
        "P",
        "N",
        1
      ]
    },
    {
      "color": "#FF5A5A5A",
      "edge_type": "rooms",
      "from": 31,
      "path": [],
      "to": 53,
      "unknown": [
        100,
        0,
        0,
        "Metadata/Terrain/Dungeon/rooms.et",
        0,
        0,
        0,
        "",
        0,
        "",
        0,
        0,
        "P",
        "N",
        1
      ]
    },
    {
      "color": "#FF5A5A5A",
      "edge_type": "rooms",
      "from": 49,
      "path": [],
      "to": 50,
      "unknown": [
        100,
        0,
        0,
        "Metadata/Terrain/Dungeon/rooms.et",
        0,
        0,
        0,
        "",
        0,
        "",
        0,
        0,
        "P",
        "N",
        1
      ]
    },
    {
      "color": "#FF5A5A5A",
      "edge_type": "rooms",
      "from": 37,
      "path": [],
      "to": 35,
      "unknown": [
        100,
        0,
        0,
        "Metadata/Terrain/Dungeon/rooms.et",
        0,
        0,
        0,
        "",
        0,
        "",
        0,
        0,
        "P",
        "N",
        1
      ]
    },
    {
      "color": "#FF5A5A5A",
      "edge_type": "rooms",
      "from": 48,
      "path": [],
      "to": 47,
      "unknown": [
        100,
        0,
        0,
        "Metadata/Terrain/Dungeon/rooms.et",
        0,
        0,
        0,
        "",
        0,
        "",
        0,
        0,
        "P",
        "N",
        1
      ]
    },
    {
      "color": "#FF5A5A5A",
      "edge_type": "rooms",
      "from": 23,
      "path": [],
      "to": 24,
      "unknown": [
        100,
        0,
        0,
        "Metadata/Terrain/Dungeon/rooms.et",
        0,
        0,
        0,
        "",
        0,
        "",
        0,
        0,
        "P",
        "N",
        1
      ]
    },
    {
      "color": "#FF5A5A5A",
      "edge_type": "rooms",
      "from": 31,
      "path": [],
      "to": 33,
      "unknown": [
        100,
        0,
        0,
        "Metadata/Terrain/Dungeon/rooms.et",
        0,
        0,
        0,
        "",
        0,
        "",
        0,
        0,
        "P",
        "N",
        1
      ]
    },
    {
      "color": "#FF5A5A5A",
      "edge_type": "rooms",
      "from": 29,
      "path": [],
      "to": 53,
      "unknown": [
        100,
        0,
        0,
        "Metadata/Terrain/Dungeon/rooms.et",
        0,
        0,
        0,
        "",
        0,
        "",
        0,
        0,
        "P",
        "N",
        1
      ]
    },
    {
      "color": "#FF5A5A5A",
      "edge_type": "rooms",
      "from": 54,
      "path": [],
      "to": 42,
      "unknown": [
        100,
        0,
        0,
        "Metadata/Terrain/Dungeon/rooms.et",
        0,
        0,
        0,
        "",
        0,
        "",
        0,
        0,
        "P",
        "N",
        1
      ]
    },
    {
      "color": "#FF5A5A5A",
      "edge_type": "rooms",
      "from": 55,
      "path": [],
      "to": 41,
      "unknown": [
        100,
        0,
        0,
        "Metadata/Terrain/Dungeon/rooms.et",
        0,
        0,
        0,
        "",
        0,
        "",
        0,
        0,
        "P",
        "N",
        1
      ]
    },
    {
      "color": "#FF5A5A5A",
      "edge_type": "rooms",
      "from": 56,
      "path": [],
      "to": 55,
      "unknown": [
        100,
        0,
        0,
        "Metadata/Terrain/Dungeon/rooms.et",
        0,
        0,
        0,
        "",
        0,
        "",
        0,
        0,
        "P",
        "N",
        1
      ]
    },
    {
      "color": "#FF5A5A5A",
      "edge_type": "rooms",
      "from": 42,
      "path": [],
      "to": 41,
      "unknown": [
        100,
        0,
        0,
        "Metadata/Terrain/Dungeon/rooms.et",
        0,
        0,
        0,
        "",
        0,
        "",
        0,
        0,
        "P",
        "N",
        1
      ]
    },
    {
      "color": "#FF5A5A5A",
      "edge_type": "rooms",
      "from": 55,
      "path": [],
      "to": 27,
      "unknown": [
        100,
        0,
        0,
        "Metadata/Terrain/Dungeon/rooms.et",
        0,
        0,
        0,
        "",
        0,
        "",
        0,
        0,
        "P",
        "N",
        1
      ]
    },
    {
      "color": "#FF141414",
      "edge_type": "void",
      "from": 57,
      "path": [],
      "to": 58,
      "unknown": [
        100,
        0,
        0,
        "Metadata/Terrain/Tools/void.et",
        0,
        0,
        0,
        "",
        0,
        "",
        0,
        0,
        "P",
        "V",
        1
      ]
    },
    {
      "color": "#FF141414",
      "edge_type": "void",
      "from": 59,
      "path": [],
      "to": 60,
      "unknown": [
        100,
        0,
        0,
        "Metadata/Terrain/Tools/void.et",
        0,
        0,
        0,
        "",
        0,
        "",
        0,
        0,
        "P",
        "V",
        1
      ]
    },
    {
      "color": "#FF141414",
      "edge_type": "void",
      "from": 61,
      "path": [],
      "to": 62,
      "unknown": [
        100,
        0,
        0,
        "Metadata/Terrain/Tools/void.et",
        0,
        0,
        0,
        "",
        0,
        "",
        0,
        0,
        "P",
        "V",
        1
      ]
    },
    {
      "color": "#FF141414",
      "edge_type": "void",
      "from": 63,
      "path": [],
      "to": 64,
      "unknown": [
        100,
        0,
        0,
        "Metadata/Terrain/Tools/void.et",
        0,
        0,
        0,
        "",
        0,
        "",
        0,
        0,
        "P",
        "V",
        1
      ]
    },
    {
      "color": "#FF141414",
      "edge_type": "void",
      "from": 65,
      "path": [],
      "to": 66,
      "unknown": [
        100,
        0,
        0,
        "Metadata/Terrain/Tools/void.et",
        0,
        0,
        0,
        "",
        0,
        "",
        0,
        0,
        "P",
        "V",
        1
      ]
    },
    {
      "color": "#FF141414",
      "edge_type": "void",
      "from": 67,
      "path": [],
      "to": 68,
      "unknown": [
        100,
        0,
        0,
        "Metadata/Terrain/Tools/void.et",
        0,
        0,
        0,
        "",
        0,
        "",
        0,
        0,
        "P",
        "V",
        1
      ]
    },
    {
      "color": "#FF141414",
      "edge_type": "void",
      "from": 69,
      "path": [],
      "to": 70,
      "unknown": [
        100,
        0,
        0,
        "Metadata/Terrain/Tools/void.et",
        0,
        0,
        0,
        "",
        0,
        "",
        0,
        0,
        "P",
        "V",
        1
      ]
    },
    {
      "color": "#FF141414",
      "edge_type": "void",
      "from": 71,
      "path": [],
      "to": 72,
      "unknown": [
        100,
        0,
        0,
        "Metadata/Terrain/Tools/void.et",
        0,
        0,
        0,
        "",
        0,
        "",
        0,
        0,
        "P",
        "V",
        1
      ]
    },
    {
      "color": "#FF5A5A5A",
      "edge_type": "rooms",
      "from": 8,
      "path": [],
      "to": 10,
      "unknown": [
        100,
        0,
        0,
        "Metadata/Terrain/Dungeon/rooms.et",
        0,
        0,
        0,
        "",
        0,
        "",
        0,
        0,
        "P",
        "N",
        1
      ]
    }
  ],
  "master": {
    "ChestData": "chests.cht",
    "Critters": "critters.clt",
    "Decals": "decals.dct",
    "Doodads": "doodads.ddt",
    "EdgeCombination": "combination.ecf",
    "FillTiles": "random_fill_tiles.gft",
    "MaterialsList": "materials.mtd",
    "OuterBufferSize": null,
    "OuterGroundType": "Metadata/Terrain/black_inside_wall.gt",
    "Overlays": "overlays.toy",
    "RoomSet": "generate.rs",
    "RoomUnitSize": null,
    "StoreyHeight": null,
    "TileMaterialOverrides": "material_overrides.tmo",
    "TileSet": "tiles.tst",
    "version": null
  },
  "node_count": 73,
  "nodes": [
    {
      "numbers": [
        0
      ],
      "room": "",
      "strings": [],
      "transform": "(best)",
      "unknown": [
        100,
        0,
        0,
        0,
        0,
        0,
        0,
        0,
        0,
        "V",
        0
      ],
      "x": 196,
      "y": 173
    },
    {
      "numbers": [
        0
      ],
      "room": "",
      "strings": [],
      "transform": "(best)",
      "unknown": [
        100,
        0,
        0,
        0,
        0,
        0,
        0,
        0,
        0,
        "V",
        0
      ],
      "x": 242,
      "y": 173
    },
    {
      "numbers": [
        1
      ],
      "room": "",
      "strings": [],
      "transform": "(best)",
      "unknown": [
        100,
        0,
        0,
        0,
        0,
        0,
        0,
        0,
        0,
        "V",
        0
      ],
      "x": 242,
      "y": 81
    },
    {
      "numbers": [
        1
      ],
      "room": "",
      "strings": [],
      "transform": "(best)",
      "unknown": [
        100,
        0,
        0,
        0,
        0,
        0,
        0,
        0,
        0,
        "V",
        0
      ],
      "x": 196,
      "y": 81
    },
    {
      "numbers": [
        2
      ],
      "room": "",
      "strings": [],
      "transform": "(best)",
      "unknown": [
        100,
        0,
        0,
        0,
        0,
        0,
        0,
        0,
        0,
        "V",
        0
      ],
      "x": 196,
      "y": 58
    },
    {
      "numbers": [
        3
      ],
      "room": "",
      "strings": [],
      "transform": "(best)",
      "unknown": [
        100,
        0,
        0,
        0,
        0,
        0,
        0,
        0,
        0,
        "V",
        0
      ],
      "x": 35,
      "y": 81
    },
    {
      "numbers": [
        3
      ],
      "room": "",
      "strings": [],
      "transform": "(best)",
      "unknown": [
        100,
        0,
        0,
        0,
        0,
        0,
        0,
        0,
        0,
        "V",
        0
      ],
      "x": 12,
      "y": 81
    },
    {
      "numbers": [
        4
      ],
      "room": "",
      "strings": [],
      "transform": "(best)",
      "unknown": [
        100,
        0,
        0,
        0,
        0,
        0,
        0,
        0,
        0,
        "V",
        0
      ],
      "x": 12,
      "y": 150
    },
    {
      "numbers": [
        62
      ],
      "room": "entrance",
      "strings": [
        "default"
      ],
      "transform": "I",
      "unknown": [
        100,
        0,
        0,
        0,
        0,
        0,
        0,
        0,
        0,
        "N",
        0
      ],
      "x": 12,
      "y": 104
    },
    {
      "numbers": [
        8,
        29,
        12,
        11
      ],
      "room": "mid",
      "strings": [],
      "transform": "I",
      "unknown": [
        100,
        0,
        0,
        0,
        0,
        0,
        0,
        0,
        0,
        "N",
        0
      ],
      "x": 58,
      "y": 104
    },
    {
      "numbers": [
        62
      ],
      "room": "endcap",
      "strings": [],
      "transform": "FI",
      "unknown": [
        100,
        0,
        0,
        0,
        0,
        0,
        0,
        0,
        0,
        "N",
        0
      ],
      "x": 196,
      "y": 104
    },
    {
      "numbers": [
        25,
        26,
        28,
        27
      ],
      "room": "mid",
      "strings": [],
      "transform": "I",
      "unknown": [
        100,
        0,
        0,
        0,
        0,
        0,
        0,
        0,
        0,
        "N",
        0
      ],
      "x": 150,
      "y": 104
    },
    {
      "numbers": [
        5
      ],
      "room": "",
      "strings": [],
      "transform": "(best)",
      "unknown": [
        100,
        0,
        0,
        0,
        0,
        0,
        0,
        0,
        0,
        "V",
        0
      ],
      "x": 12,
      "y": 173
    },
    {
      "numbers": [
        5
      ],
      "room": "",
      "strings": [],
      "transform": "(best)",
      "unknown": [
        100,
        0,
        0,
        0,
        0,
        0,
        0,
        0,
        0,
        "V",
        0
      ],
      "x": 35,
      "y": 173
    },
    {
      "numbers": [
        6
      ],
      "room": "",
      "strings": [],
      "transform": "(best)",
      "unknown": [
        100,
        0,
        0,
        0,
        0,
        0,
        0,
        0,
        0,
        "V",
        0
      ],
      "x": 12,
      "y": 58
    },
    {
      "numbers": [
        6
      ],
      "room": "",
      "strings": [],
      "transform": "(best)",
      "unknown": [
        100,
        0,
        0,
        0,
        0,
        0,
        0,
        0,
        0,
        "V",
        0
      ],
      "x": 35,
      "y": 58
    },
    {
      "numbers": [
        7
      ],
      "room": "",
      "strings": [],
      "transform": "(best)",
      "unknown": [
        100,
        0,
        0,
        0,
        0,
        0,
        0,
        0,
        0,
        "V",
        0
      ],
      "x": 242,
      "y": 150
    },
    {
      "numbers": [
        7
      ],
      "room": "",
      "strings": [],
      "transform": "(best)",
      "unknown": [
        100,
        0,
        0,
        0,
        0,
        0,
        0,
        0,
        0,
        "V",
        0
      ],
      "x": 196,
      "y": 150
    },
    {
      "numbers": [
        2
      ],
      "room": "",
      "strings": [],
      "transform": "(best)",
      "unknown": [
        100,
        0,
        0,
        0,
        0,
        0,
        0,
        0,
        0,
        "V",
        0
      ],
      "x": 242,
      "y": 58
    },
    {
      "numbers": [
        4
      ],
      "room": "",
      "strings": [],
      "transform": "(best)",
      "unknown": [
        100,
        0,
        0,
        0,
        0,
        0,
        0,
        0,
        0,
        "V",
        0
      ],
      "x": 35,
      "y": 150
    },
    {
      "numbers": [
        41,
        40,
        22,
        21
      ],
      "room": "mid",
      "strings": [],
      "transform": "I",
      "unknown": [
        100,
        0,
        0,
        0,
        0,
        0,
        0,
        0,
        0,
        "N",
        0
      ],
      "x": 104,
      "y": 104
    },
    {
      "numbers": [
        9
      ],
      "room": "end",
      "strings": [],
      "transform": "(best)",
      "unknown": [
        100,
        0,
        0,
        0,
        0,
        0,
        0,
        0,
        0,
        "N",
        0
      ],
      "x": 58,
      "y": 173
    },
    {
      "numbers": [
        36
      ],
      "room": "end",
      "strings": [],
      "transform": "(best)",
      "unknown": [
        100,
        0,
        0,
        0,
        0,
        0,
        0,
        0,
        0,
        "N",
        0
      ],
      "x": 81,
      "y": 196
    },
    {
      "numbers": [
        12,
        10,
        46
      ],
      "room": "tri",
      "strings": [],
      "transform": "(best)",
      "unknown": [
        100,
        0,
        0,
        0,
        0,
        0,
        0,
        0,
        0,
        "N",
        0
      ],
      "x": 81,
      "y": 150
    },
    {
      "numbers": [
        11,
        46,
        9
      ],
      "room": "tri",
      "strings": [],
      "transform": "(best)",
      "unknown": [
        100,
        0,
        0,
        0,
        0,
        0,
        0,
        0,
        0,
        "N",
        0
      ],
      "x": 58,
      "y": 150
    },
    {
      "numbers": [
        21,
        37
      ],
      "room": "st",
      "strings": [],
      "transform": "(best)",
      "unknown": [
        100,
        0,
        0,
        0,
        0,
        0,
        0,
        0,
        0,
        "N",
        0
      ],
      "x": 104,
      "y": 150
    },
    {
      "numbers": [
        20
      ],
      "room": "end",
      "strings": [],
      "transform": "(best)",
      "unknown": [
        100,
        0,
        0,
        0,
        0,
        0,
        0,
        0,
        0,
        "N",
        0
      ],
      "x": 104,
      "y": 219
    },
    {
      "numbers": [
        30,
        23,
        53
      ],
      "room": "tri",
      "strings": [],
      "transform": "(best)",
      "unknown": [
        100,
        0,
        0,
        0,
        0,
        0,
        0,
        0,
        0,
        "N",
        0
      ],
      "x": 104,
      "y": 58
    },
    {
      "numbers": [
        13
      ],
      "room": "end",
      "strings": [],
      "transform": "(best)",
      "unknown": [
        100,
        0,
        0,
        0,
        0,
        0,
        0,
        0,
        0,
        "N",
        0
      ],
      "x": 104,
      "y": 12
    },
    {
      "numbers": [
        31,
        48,
        24
      ],
      "room": "tri",
      "strings": [],
      "transform": "(best)",
      "unknown": [
        100,
        0,
        0,
        0,
        0,
        0,
        0,
        0,
        0,
        "N",
        0
      ],
      "x": 127,
      "y": 58
    },
    {
      "numbers": [
        14
      ],
      "room": "end",
      "strings": [],
      "transform": "(best)",
      "unknown": [
        100,
        0,
        0,
        0,
        0,
        0,
        0,
        0,
        0,
        "N",
        0
      ],
      "x": 127,
      "y": 12
    },
    {
      "numbers": [
        42,
        47,
        25
      ],
      "room": "tri",
      "strings": [],
      "transform": "(best)",
      "unknown": [
        100,
        0,
        0,
        0,
        0,
        0,
        0,
        0,
        0,
        "N",
        0
      ],
      "x": 150,
      "y": 81
    },
    {
      "numbers": [
        15
      ],
      "room": "end",
      "strings": [],
      "transform": "(best)",
      "unknown": [
        100,
        0,
        0,
        0,
        0,
        0,
        0,
        0,
        0,
        "N",
        0
      ],
      "x": 150,
      "y": 35
    },
    {
      "numbers": [
        16,
        26,
        47
      ],
      "room": "tri",
      "strings": [],
      "transform": "(best)",
      "unknown": [
        100,
        0,
        0,
        0,
        0,
        0,
        0,
        0,
        0,
        "N",
        0
      ],
      "x": 173,
      "y": 81
    },
    {
      "numbers": [
        16
      ],
      "room": "end",
      "strings": [],
      "transform": "(best)",
      "unknown": [
        100,
        0,
        0,
        0,
        0,
        0,
        0,
        0,
        0,
        "N",
        0
      ],
      "x": 173,
      "y": 58
    },
    {
      "numbers": [
        28,
        17,
        44
      ],
      "room": "tri",
      "strings": [],
      "transform": "(best)",
      "unknown": [
        100,
        0,
        0,
        0,
        0,
        0,
        0,
        0,
        0,
        "N",
        0
      ],
      "x": 173,
      "y": 150
    },
    {
      "numbers": [
        17
      ],
      "room": "end",
      "strings": [],
      "transform": "(best)",
      "unknown": [
        100,
        0,
        0,
        0,
        0,
        0,
        0,
        0,
        0,
        "N",
        0
      ],
      "x": 173,
      "y": 173
    },
    {
      "numbers": [
        27,
        44,
        39
      ],
      "room": "tri",
      "strings": [],
      "transform": "(best)",
      "unknown": [
        100,
        0,
        0,
        0,
        0,
        0,
        0,
        0,
        0,
        "N",
        0
      ],
      "x": 150,
      "y": 150
    },
    {
      "numbers": [
        18
      ],
      "room": "end",
      "strings": [],
      "transform": "(best)",
      "unknown": [
        100,
        0,
        0,
        0,
        0,
        0,
        0,
        0,
        0,
        "N",
        0
      ],
      "x": 150,
      "y": 196
    },
    {
      "numbers": [
        22,
        38
      ],
      "room": "st",
      "strings": [],
      "transform": "(best)",
      "unknown": [
        100,
        0,
        0,
        0,
        0,
        0,
        0,
        0,
        0,
        "N",
        0
      ],
      "x": 127,
      "y": 150
    },
    {
      "numbers": [
        19
      ],
      "room": "end",
      "strings": [],
      "transform": "(best)",
      "unknown": [
        100,
        0,
        0,
        0,
        0,
        0,
        0,
        0,
        0,
        "N",
        0
      ],
      "x": 127,
      "y": 219
    },
    {
      "numbers": [
        50,
        29,
        52
      ],
      "room": "tri",
      "strings": [],
      "transform": "(best)",
      "unknown": [
        100,
        0,
        0,
        0,
        0,
        0,
        0,
        0,
        0,
        "N",
        0
      ],
      "x": 81,
      "y": 81
    },
    {
      "numbers": [
        49,
        52,
        8
      ],
      "room": "tri",
      "strings": [],
      "transform": "(best)",
      "unknown": [
        100,
        0,
        0,
        0,
        0,
        0,
        0,
        0,
        0,
        "N",
        0
      ],
      "x": 58,
      "y": 81
    },
    {
      "numbers": [
        13,
        32,
        30
      ],
      "room": "tri",
      "strings": [],
      "transform": "(best)",
      "unknown": [
        100,
        0,
        0,
        0,
        0,
        0,
        0,
        0,
        0,
        "N",
        0
      ],
      "x": 104,
      "y": 35
    },
    {
      "numbers": [
        14,
        31,
        32
      ],
      "room": "tri",
      "strings": [],
      "transform": "(best)",
      "unknown": [
        100,
        0,
        0,
        0,
        0,
        0,
        0,
        0,
        0,
        "N",
        0
      ],
      "x": 127,
      "y": 35
    },
    {
      "numbers": [
        33,
        35,
        20
      ],
      "room": "tri",
      "strings": [],
      "transform": "(best)",
      "unknown": [
        100,
        0,
        0,
        0,
        0,
        0,
        0,
        0,
        0,
        "N",
        0
      ],
      "x": 104,
      "y": 196
    },
    {
      "numbers": [
        34,
        19,
        35
      ],
      "room": "tri",
      "strings": [],
      "transform": "(best)",
      "unknown": [
        100,
        0,
        0,
        0,
        0,
        0,
        0,
        0,
        0,
        "N",
        0
      ],
      "x": 127,
      "y": 196
    },
    {
      "numbers": [
        10,
        45,
        36
      ],
      "room": "tri",
      "strings": [],
      "transform": "(best)",
      "unknown": [
        100,
        0,
        0,
        0,
        0,
        0,
        0,
        0,
        0,
        "N",
        0
      ],
      "x": 81,
      "y": 173
    },
    {
      "numbers": [
        37,
        33,
        45
      ],
      "room": "tri",
      "strings": [],
      "transform": "(best)",
      "unknown": [
        100,
        0,
        0,
        0,
        0,
        0,
        0,
        0,
        0,
        "N",
        0
      ],
      "x": 104,
      "y": 173
    },
    {
      "numbers": [
        38,
        43,
        34
      ],
      "room": "tri",
      "strings": [],
      "transform": "(best)",
      "unknown": [
        100,
        0,
        0,
        0,
        0,
        0,
        0,
        0,
        0,
        "N",
        0
      ],
      "x": 127,
      "y": 173
    },
    {
      "numbers": [
        39,
        18,
        43
      ],
      "room": "tri",
      "strings": [],
      "transform": "(best)",
      "unknown": [
        100,
        0,
        0,
        0,
        0,
        0,
        0,
        0,
        0,
        "N",
        0
      ],
      "x": 150,
      "y": 173
    },
    {
      "numbers": [
        24,
        40
      ],
      "room": "st",
      "strings": [],
      "transform": "(best)",
      "unknown": [
        100,
        0,
        0,
        0,
        0,
        0,
        0,
        0,
        0,
        "N",
        0
      ],
      "x": 127,
      "y": 81
    },
    {
      "numbers": [
        23,
        41
      ],
      "room": "st",
      "strings": [],
      "transform": "(best)",
      "unknown": [
        100,
        0,
        0,
        0,
        0,
        0,
        0,
        0,
        0,
        "N",
        0
      ],
      "x": 104,
      "y": 81
    },
    {
      "numbers": [
        15,
        42,
        48
      ],
      "room": "tri",
      "strings": [],
      "transform": "(best)",
      "unknown": [
        100,
        0,
        0,
        0,
        0,
        0,
        0,
        0,
        0,
        "N",
        0
      ],
      "x": 150,
      "y": 58
    },
    {
      "numbers": [
        49
      ],
      "room": "end",
      "strings": [],
      "transform": "(best)",
      "unknown": [
        100,
        0,
        0,
        0,
        0,
        0,
        0,
        0,
        0,
        "N",
        0
      ],
      "x": 58,
      "y": 58
    },
    {
      "numbers": [
        51,
        53,
        50
      ],
      "room": "tri",
      "strings": [],
      "transform": "(best)",
      "unknown": [
        100,
        0,
        0,
        0,
        0,
        0,
        0,
        0,
        0,
        "N",
        0
      ],
      "x": 81,
      "y": 58
    },
    {
      "numbers": [
        51
      ],
      "room": "end",
      "strings": [],
      "transform": "(best)",
      "unknown": [
        100,
        0,
        0,
        0,
        0,
        0,
        0,
        0,
        0,
        "N",
        0
      ],
      "x": 81,
      "y": 35
    },
    {
      "numbers": [
        54
      ],
      "room": "",
      "strings": [],
      "transform": "(best)",
      "unknown": [
        100,
        0,
        0,
        0,
        0,
        0,
        0,
        0,
        0,
        "V",
        0
      ],
      "x": 12,
      "y": 196
    },
    {
      "numbers": [
        54
      ],
      "room": "",
      "strings": [],
      "transform": "(best)",
      "unknown": [
        100,
        0,
        0,
        0,
        0,
        0,
        0,
        0,
        0,
        "V",
        0
      ],
      "x": 58,
      "y": 196
    },
    {
      "numbers": [
        55
      ],
      "room": "",
      "strings": [],
      "transform": "(best)",
      "unknown": [
        100,
        0,
        0,
        0,
        0,
        0,
        0,
        0,
        0,
        "V",
        0
      ],
      "x": 12,
      "y": 219
    },
    {
      "numbers": [
        55
      ],
      "room": "",
      "strings": [],
      "transform": "(best)",
      "unknown": [
        100,
        0,
        0,
        0,
        0,
        0,
        0,
        0,
        0,
        "V",
        0
      ],
      "x": 81,
      "y": 219
    },
    {
      "numbers": [
        56
      ],
      "room": "",
      "strings": [],
      "transform": "(best)",
      "unknown": [
        100,
        0,
        0,
        0,
        0,
        0,
        0,
        0,
        0,
        "V",
        0
      ],
      "x": 150,
      "y": 219
    },
    {
      "numbers": [
        56
      ],
      "room": "",
      "strings": [],
      "transform": "(best)",
      "unknown": [
        100,
        0,
        0,
        0,
        0,
        0,
        0,
        0,
        0,
        "V",
        0
      ],
      "x": 242,
      "y": 219
    },
    {
      "numbers": [
        57
      ],
      "room": "",
      "strings": [],
      "transform": "(best)",
      "unknown": [
        100,
        0,
        0,
        0,
        0,
        0,
        0,
        0,
        0,
        "V",
        0
      ],
      "x": 173,
      "y": 196
    },
    {
      "numbers": [
        57
      ],
      "room": "",
      "strings": [],
      "transform": "(best)",
      "unknown": [
        100,
        0,
        0,
        0,
        0,
        0,
        0,
        0,
        0,
        "V",
        0
      ],
      "x": 242,
      "y": 196
    },
    {
      "numbers": [
        58
      ],
      "room": "",
      "strings": [],
      "transform": "(best)",
      "unknown": [
        100,
        0,
        0,
        0,
        0,
        0,
        0,
        0,
        0,
        "V",
        0
      ],
      "x": 173,
      "y": 35
    },
    {
      "numbers": [
        58
      ],
      "room": "",
      "strings": [],
      "transform": "(best)",
      "unknown": [
        100,
        0,
        0,
        0,
        0,
        0,
        0,
        0,
        0,
        "V",
        0
      ],
      "x": 242,
      "y": 35
    },
    {
      "numbers": [
        59
      ],
      "room": "",
      "strings": [],
      "transform": "(best)",
      "unknown": [
        100,
        0,
        0,
        0,
        0,
        0,
        0,
        0,
        0,
        "V",
        0
      ],
      "x": 150,
      "y": 12
    },
    {
      "numbers": [
        59
      ],
      "room": "",
      "strings": [],
      "transform": "(best)",
      "unknown": [
        100,
        0,
        0,
        0,
        0,
        0,
        0,
        0,
        0,
        "V",
        0
      ],
      "x": 242,
      "y": 12
    },
    {
      "numbers": [
        60
      ],
      "room": "",
      "strings": [],
      "transform": "(best)",
      "unknown": [
        100,
        0,
        0,
        0,
        0,
        0,
        0,
        0,
        0,
        "V",
        0
      ],
      "x": 81,
      "y": 12
    },
    {
      "numbers": [
        60
      ],
      "room": "",
      "strings": [],
      "transform": "(best)",
      "unknown": [
        100,
        0,
        0,
        0,
        0,
        0,
        0,
        0,
        0,
        "V",
        0
      ],
      "x": 12,
      "y": 12
    },
    {
      "numbers": [
        61
      ],
      "room": "",
      "strings": [],
      "transform": "(best)",
      "unknown": [
        100,
        0,
        0,
        0,
        0,
        0,
        0,
        0,
        0,
        "V",
        0
      ],
      "x": 12,
      "y": 35
    },
    {
      "numbers": [
        61
      ],
      "room": "",
      "strings": [],
      "transform": "(best)",
      "unknown": [
        100,
        0,
        0,
        0,
        0,
        0,
        0,
        0,
        0,
        "V",
        0
      ],
      "x": 58,
      "y": 35
    }
  ],
  "numbers": [
    0
  ],
  "room_set": [],
  "size": [
    11,
    10
  ],
  "strings": [
    "",
    "",
    ""
  ],
  "tile_set": [
    {
      "file": "Metadata/Terrain/Dungeon/TreasureVault/SmeltingPot_02.tdt",
      "suffix": [
        "FI",
        "FR90",
        "FR180",
        "FR270"
      ]
    },
    {
      "file": "Metadata/Terrain/Dungeon/TreasureVault/TreasureWingInnerEntrance_01.tdt",
      "prefix": [
        "//"
      ],
      "suffix": [
        "I",
        "FI",
        "R90",
        "FR90"
      ]
    },
    {
      "file": "Metadata/Terrain/Dungeon/TreasureVault/VaultThickChestSt_01.tdt",
      "prefix": [
        "//"
      ],
      "suffix": [
        "I",
        "FI",
        "R270",
        "FR270"
      ]
    },
    {
      "file": "Metadata/Terrain/Dungeon/TreasureVault/VaultThickDownscreenNoChestSt_01.tdt",
      "prefix": [
        "//"
      ],
      "suffix": [
        "R90",
        "FR90",
        "R180",
        "FR180"
      ]
    }
  ],
  "version": 25
}