[
  {
    "English": null,
    "ids": [
      "spiral_volley_X_chains_per_frenzy_charge_consumed"
    ],
    "trade_stats": null,
    "hidden": null,
    "French": null,
    "German": null,
    "Japanese": null,
    "Korean": null,
    "Portuguese": null,
    "Russian": null,
    "Spanish": null,
    "Thai": [
      {
        "condition": [
          {
            "min": null,
            "max": null,
            "negated": null
          }
        ],
        "format": [
          "#"
        ],
        "index_handlers": [
          []
        ],
        "string": "จำนวนครั้ง ของการ[Chain|ชิ่ง]ต่อจำนวน [Charges|Frenzy Charge] ที่กลืนกิน@{0}%",
        "reminder_text": null,
        "is_markup": null
      },
      {
        "condition": [
          {
            "min": 1,
            "max": 1,
            "negated": null
          }
        ],
        "format": [
          "ignore"
        ],
        "index_handlers": [
          []
        ],
        "string": "[Chain|ชิ่ง] 1 ครั้งต่อจำนวน [Charges|Frenzy Charge] ที่กลืนกิน",
        "reminder_text": null,
        "is_markup": null
      },
      {
        "condition": [
          {
            "min": 2,
            "max": null,
            "negated": null
          }
        ],
        "format": [
          "#"
        ],
        "index_handlers": [
          []
        ],
        "string": "[Chain|ชิ่ง] {0} ครั้งต่อจำนวน [Charges|Frenzy Charge] ที่กลืนกิน",
        "reminder_text": null,
        "is_markup": null
      }
    ],
    "Traditional_Chinese": null
  },
  {
    "English": null,
    "ids": [
      "spiral_volley_damage_+%_final_per_frenzy_charge_consumed"
    ],
    "trade_stats": null,
    "hidden": null,
    "French": null,
    "German": null,
    "Japanese": null,
    "Korean": null,
    "Portuguese": null,
    "Russian": null,
    "Spanish": null,
    "Thai": [
      {
        "condition": [
          {
            "min": null,
            "max": null,
            "negated": null
          }
        ],
        "format": [
          "#"
        ],
        "index_handlers": [
          []
        ],
        "string": "ความเสียหาย ที่เพิ่มขึ้น อีก ต่อจำนวน [Charges|Frenzy Charge] ที่กลืนกิน@{0}%",
        "reminder_text": null,
        "is_markup": null
      },
      {
        "condition": [
          {
            "min": 1,
            "max": null,
            "negated": null
          }
        ],
        "format": [
          "#"
        ],
        "index_handlers": [
          []
        ],
        "string": "เพิ่มความเสียหาย อีก {0}% ต่อจำนวน [Charges|Frenzy Charge] ที่กลืนกิน",
        "reminder_text": null,
        "is_markup": null
      },
      {
        "condition": [
          {
            "min": null,
            "max": -1,
            "negated": null
          }
        ],
        "format": [
          "#"
        ],
        "index_handlers": [
          [
            "negate"
          ]
        ],
        "string": "ลดความเสียหาย อีก {0}% ต่อจำนวน [Charges|Frenzy Charge] ที่กลืนกิน",
        "reminder_text": null,
        "is_markup": null
      }
    ],
    "Traditional_Chinese": null
  },
  {
    "English": null,
    "ids": [
      "spiral_volley_damage_+%_final_when_frenzy_charges_consumed"
    ],
    "trade_stats": null,
    "hidden": null,
    "French": null,
    "German": null,
    "Japanese": null,
    "Korean": null,
    "Portuguese": null,
    "Russian": null,
    "Spanish": null,
    "Thai": [
      {
        "condition": [
          {
            "min": null,
            "max": null,
            "negated": null
          }
        ],
        "format": [
          "#"
        ],
        "index_handlers": [
          []
        ],
        "string": "ความเสียหาย ที่เพิ่มขึ้น อีก หากกลืนกิน [Charges|Frenzy Charge]@{0}%",
        "reminder_text": null,
        "is_markup": null
      },
      {
        "condition": [
          {
            "min": 1,
            "max": null,
            "negated": null
          }
        ],
        "format": [
          "#"
        ],
        "index_handlers": [
          []
        ],
        "string": "เพิ่มความเสียหาย อีก {0}% หากกลืนกิน [Charges|Frenzy Charge]",
        "reminder_text": null,
        "is_markup": null
      },
      {
        "condition": [
          {
            "min": null,
            "max": -1,
            "negated": null
          }
        ],
        "format": [
          "#"
        ],
        "index_handlers": [
          [
            "negate"
          ]
        ],
        "string": "ลดความเสียหาย อีก {0}% หากกลืนกิน [Charges|Frenzy Charge]",
        "reminder_text": null,
        "is_markup": null
      }
    ],
    "Traditional_Chinese": null
  }
]